plumb/__init__.py
plumb/king/__init__.py
plumb/king/cli.py
plumb/king/exif_utils.py
plumb/king/fs_scanner.py
plumb/king/leveling_apply.py
plumb/king/leveling_core.py
plumb/king/naming.py
plumb/king/thumbnails.py
plumbking-0.1.1.dist-info/licenses/LICENSE
plumbking-0.1.1.dist-info/licenses/LICENSE_OVERVIEW.md
plumbking-0.1.1.dist-info/METADATA
plumbking-0.1.1.dist-info/WHEEL
plumbking-0.1.1.dist-info/entry_points.txt
plumbking-0.1.1.dist-info/top_level.txt
plumbking-0.1.1.dist-info/RECORD
