Metadata-Version: 2.4
Name: plumbking
Version: 0.1.1
Summary: Classical CV-based image leveling and thumbnail generator.
Home-page: https://github.com/your-user/plumbking
Author: 
License: AGPL-3.0-or-later
Classifier: Programming Language :: Python
Classifier: Programming Language :: Python :: 3
Classifier: Programming Language :: Python :: 3 :: Only
Classifier: License :: OSI Approved :: GNU Affero General Public License v3 or later (AGPLv3+)
Classifier: Operating System :: OS Independent
Classifier: Topic :: Multimedia :: Graphics
Classifier: Topic :: Multimedia :: Graphics :: Graphics Conversion
Classifier: Intended Audience :: Developers
Classifier: Intended Audience :: System Administrators
Requires-Python: >=3.8
License-File: LICENSE
License-File: LICENSE_OVERVIEW.md
Requires-Dist: numpy>=1.22
Requires-Dist: opencv-python>=4.8
Requires-Dist: Pillow>=9.0
Requires-Dist: scikit-learn==1.7.*
Dynamic: classifier
Dynamic: description
Dynamic: description-content-type
Dynamic: home-page
Dynamic: license
Dynamic: license-file
Dynamic: requires-dist
Dynamic: requires-python
Dynamic: summary
